pydict2json/__init__.py
pydict2json/__main__.py
pydict2json-0.1.0.dist-info/LICENSE
pydict2json-0.1.0.dist-info/METADATA
pydict2json-0.1.0.dist-info/WHEEL
pydict2json-0.1.0.dist-info/entry_points.txt
pydict2json-0.1.0.dist-info/top_level.txt
pydict2json-0.1.0.dist-info/RECORD
