Metadata-Version: 2.1
Name: pydict2json
Version: 0.1.0
Summary: Given a printed python dict, convert it to JSON
Home-page: https://github.com/ralexander-phi/python-str-dict-to-json
Author: Robert Alexander
Author-email: raalexander.phi@gmail.com
License: MIT
Platform: UNKNOWN
Classifier: Development Status :: 4 - Beta
Classifier: Environment :: Console
Classifier: Intended Audience :: Developers
Classifier: License :: OSI Approved :: MIT License
Classifier: Operating System :: OS Independent
Classifier: Programming Language :: Python :: 3
Classifier: Programming Language :: Python
Classifier: Topic :: Utilities
Requires-Python: >=3.6
Requires-Dist: click (>=7.1.2)
